LICENSE
MANIFEST.in
README.rst
setup.py
devlpr/__init__.py
devlpr.egg-info/PKG-INFO
devlpr.egg-info/SOURCES.txt
devlpr.egg-info/dependency_links.txt
devlpr.egg-info/top_level.txt
devlpr/tests/__init__.py